AUTHORS.rst
ChangeLog.rst
LICENSE
MANIFEST.in
README.rst
setup.py
stop_words/__init__.py
stop_words/tests.py
stop_words.egg-info/PKG-INFO
stop_words.egg-info/SOURCES.txt
stop_words.egg-info/dependency_links.txt
stop_words.egg-info/top_level.txt
stop_words/stop-words/arabic.txt
stop_words/stop-words/catalan.txt
stop_words/stop-words/danish.txt
stop_words/stop-words/dutch.txt
stop_words/stop-words/english.txt
stop_words/stop-words/finnish.txt
stop_words/stop-words/french.txt
stop_words/stop-words/german.txt
stop_words/stop-words/hungarian.txt
stop_words/stop-words/italian.txt
stop_words/stop-words/norwegian.txt
stop_words/stop-words/portuguese.txt
stop_words/stop-words/romanian.txt
stop_words/stop-words/russian.txt
stop_words/stop-words/spanish.txt
stop_words/stop-words/swedish.txt
stop_words/stop-words/turkish.txt
stop_words/stop-words/ukrainian.txt