Metadata-Version: 1.1
Name: stop-words
Version: 2015.2.21
Summary: Get list of common stop words in various languages in Python
Home-page: https://github.com/Alir3z4/python-stop-words
Author: Alireza Savand
Author-email: alireza.savand@gmail.com
License: Copyright (c) 2014, Alireza Savand, Contributors
